LINZ/Geodetic/Ellipsoid.py
LINZ/Geodetic/ITRF.py
LINZ/Geodetic/Sinex.py
linz_geodetic-1.0.0.dist-info/LICENSE
linz_geodetic-1.0.0.dist-info/WHEEL
linz_geodetic-1.0.0.dist-info/METADATA
linz_geodetic-1.0.0.dist-info/RECORD
