Metadata-Version: 2.1
Name: linz-geodetic
Version: 1.0.0
Summary: LINZ.geodetic module - miscellanous geodetic functions
Home-page: https://github.com/linz/python-linz-geodetic
License: MIT
Author: Chris Crook
Author-email: ccrook@linz.govt.nz
Requires-Python: >=3.10,<4.0
Classifier: License :: OSI Approved :: MIT License
Classifier: Programming Language :: Python :: 3
Classifier: Programming Language :: Python :: 3.10
Requires-Dist: numpy (>=1.21,<2.0)
